CHANGELOG.md
LICENSE
clown_sort/__init__.py
clown_sort/config.py
clown_sort/filename_extractor.py
clown_sort/files/image_file.py
clown_sort/files/import pdfplumber.py
clown_sort/files/pdf_file.py
clown_sort/files/sortable_file.py
clown_sort/lib/page_range.py
clown_sort/lib/rule_match.py
clown_sort/sort_rule.py
clown_sort/sort_selector.py
clown_sort/sorting_rules/crypto.csv
clown_sort/util/argument_parser.py
clown_sort/util/constants.py
clown_sort/util/dict_helper.py
clown_sort/util/filesystem_helper.py
clown_sort/util/logging.py
clown_sort/util/rich_helper.py
clown_sort/util/string_helper.py
clown_sort-1.14.1.dist-info/LICENSE
clown_sort-1.14.1.dist-info/METADATA
clown_sort-1.14.1.dist-info/WHEEL
clown_sort-1.14.1.dist-info/entry_points.txt
clown_sort-1.14.1.dist-info/RECORD
