Metadata-Version: 2.1
Name: clown_sort
Version: 1.14.1
Summary: Sort screenshots based on rules or through individual review.
Home-page: https://github.com/michelcrypt4d4mus/clown_sort
Keywords: ocr,organization,organizer,screenshot,rename,sort
Author: Michel de Cryptadamus
Author-email: michel@cryptadamus.com
Requires-Python: >=3.11.14,<4.0.0
Classifier: Programming Language :: Python :: 3
Classifier: Topic :: Desktop Environment :: File Managers
Classifier: Topic :: Multimedia :: Graphics :: Capture
Classifier: Topic :: Multimedia :: Graphics :: Capture :: Screen Capture
Classifier: Topic :: Scientific/Engineering :: Image Processing
Provides-Extra: gui
Requires-Dist: FreeSimpleGUI (>=5.2,<6.0) ; extra == "gui"
Requires-Dist: exif (>=1.5.0,<2.0.0)
Requires-Dist: filedate (>=2.0,<3.0)
Requires-Dist: pdfalyzer[extract] (>=1.17.11,<2.0.0)
Requires-Dist: piexif (>=1.1.3,<2.0.0)
Requires-Dist: pillow (>=9.5.0,<11.0.0)
Requires-Dist: pyexiftool (>=0.5.5,<0.6.0)
Requires-Dist: pypdf (>=6.0.0,<7.0.0)
Requires-Dist: pytesseract (>=0.3.13,<0.4.0)
Requires-Dist: python-dotenv (>=1.1.1,<2.0.0)
Requires-Dist: rich (>=14.1.0,<15.0.0)
Requires-Dist: rich-argparse-plus (>=0.3.1.4,<0.4.0.0)
Requires-Dist: unidecode (>=1.3.8,<2.0.0)
Project-URL: Changelog, https://github.com/michelcrypt4d4mus/clown_sort/blob/main/CHANGELOG.md
